README.md
setup.py
encryption/__init__.py
encryption/encryption.py
v_encryption.egg-info/PKG-INFO
v_encryption.egg-info/SOURCES.txt
v_encryption.egg-info/dependency_links.txt
v_encryption.egg-info/requires.txt
v_encryption.egg-info/top_level.txt